{
  "metadata" : {
    "identifier" : "https://nhattruyenz.com/truyen-tranh/thai-tu-myolyeong",
    "title" : "Thái Tử Myolyeong",
    "subtitle" : null,
    "author" : null,
    "narrator" : null,
    "language" : "vi",
    "description" : null,
    "publisher" : "N/A",
    "subject" : null,
    "modified" : null,
    "published" : "2023-05-01",
    "duration" : 0,
    "abridged" : false,
    "conformsTo" : "https://readium.org/webpub-manifest/profiles/divina",
    "numberOfPages" : 142,
    "readingProgression" : "ttb",
    "belongsTo" : null,
    "presentation" : {
      "fit" : "width",
      "overflow" : "scrolled",
      "continuous" : true
    },
    "@type" : null,
    "schema:license" : null
  },
  "links" : [ {
    "rel" : "self",
    "href" : "https://raw.githubusercontent.com/thuvienonline40/book_storage_collection/main/comic_manifest.json",
    "type" : "application/divina+json"
  } ],
  "readingOrder" : [ {
    "href" : "https://raw.githubusercontent.com/tracuumasothue40/comic_storage_two9/main/IMAGE/IMAGE_5777b5be966994190e6058da30b0f6c6_08e945681c92b9f4a36b14e7b854ff02_efb66d4604c3664f40b7680692974275.jpg",
    "type" : "image/jpeg",
    "bitrate" : 0,
    "duration" : 0,
    "title" : null,
    "properties" : null,
    "alternate" : [ {
      "href" : "https://img.abctruyen.xyz/uploads/19599/chuong-32-2/1.jpg",
      "type" : "image/jpeg",
      "bitrate" : 0,
      "duration" : 0,
      "title" : null,
      "properties" : null,
      "alternate" : null
    }, {
      "href" : "https://i2.wp.com/img.abctruyen.xyz/uploads/19599/chuong-32-2/1.jpg",
      "type" : "image/jpeg",
      "bitrate" : 0,
      "duration" : 0,
      "title" : null,
      "properties" : null,
      "alternate" : null
    } ]
  }, {
    "href" : "https://raw.githubusercontent.com/tracuumasothue40/comic_storage_two9/main/IMAGE/IMAGE_5777b5be966994190e6058da30b0f6c6_08e945681c92b9f4a36b14e7b854ff02_6abefc997b9396e8e761f9754f83bc81.jpg",
    "type" : "image/jpeg",
    "bitrate" : 0,
    "duration" : 0,
    "title" : null,
    "properties" : null,
    "alternate" : [ {
      "href" : "https://img.abctruyen.xyz/uploads/19599/chuong-32-2/2.jpg",
      "type" : "image/jpeg",
      "bitrate" : 0,
      "duration" : 0,
      "title" : null,
      "properties" : null,
      "alternate" : null
    }, {
      "href" : "https://i2.wp.com/img.abctruyen.xyz/uploads/19599/chuong-32-2/2.jpg",
      "type" : "image/jpeg",
      "bitrate" : 0,
      "duration" : 0,
      "title" : null,
      "properties" : null,
      "alternate" : null
    } ]
  }, {
    "href" : "https://raw.githubusercontent.com/tracuumasothue40/comic_storage_two9/main/IMAGE/IMAGE_5777b5be966994190e6058da30b0f6c6_08e945681c92b9f4a36b14e7b854ff02_a6d4e23fed78737902245cf78afcef16.jpg",
    "type" : "image/jpeg",
    "bitrate" : 0,
    "duration" : 0,
    "title" : null,
    "properties" : null,
    "alternate" : [ {
      "href" : "https://img.abctruyen.xyz/uploads/19599/chuong-32-2/3.jpg",
      "type" : "image/jpeg",
      "bitrate" : 0,
      "duration" : 0,
      "title" : null,
      "properties" : null,
      "alternate" : null
    }, {
      "href" : "https://i2.wp.com/img.abctruyen.xyz/uploads/19599/chuong-32-2/3.jpg",
      "type" : "image/jpeg",
      "bitrate" : 0,
      "duration" : 0,
      "title" : null,
      "properties" : null,
      "alternate" : null
    } ]
  }, {
    "href" : "https://raw.githubusercontent.com/tracuumasothue40/comic_storage_two9/main/IMAGE/IMAGE_5777b5be966994190e6058da30b0f6c6_08e945681c92b9f4a36b14e7b854ff02_7976b069ecb62515e38453056c037b76.jpg",
    "type" : "image/jpeg",
    "bitrate" : 0,
    "duration" : 0,
    "title" : null,
    "properties" : null,
    "alternate" : [ {
      "href" : "https://img.abctruyen.xyz/uploads/19599/chuong-32-2/4.jpg",
      "type" : "image/jpeg",
      "bitrate" : 0,
      "duration" : 0,
      "title" : null,
      "properties" : null,
      "alternate" : null
    }, {
      "href" : "https://i2.wp.com/img.abctruyen.xyz/uploads/19599/chuong-32-2/4.jpg",
      "type" : "image/jpeg",
      "bitrate" : 0,
      "duration" : 0,
      "title" : null,
      "properties" : null,
      "alternate" : null
    } ]
  }, {
    "href" : "https://raw.githubusercontent.com/tracuumasothue40/comic_storage_two9/main/IMAGE/IMAGE_5777b5be966994190e6058da30b0f6c6_08e945681c92b9f4a36b14e7b854ff02_dd455b55ed8dfdfb37437170559714e5.jpg",
    "type" : "image/jpeg",
    "bitrate" : 0,
    "duration" : 0,
    "title" : null,
    "properties" : null,
    "alternate" : [ {
      "href" : "https://img.abctruyen.xyz/uploads/19599/chuong-32-2/5.jpg",
      "type" : "image/jpeg",
      "bitrate" : 0,
      "duration" : 0,
      "title" : null,
      "properties" : null,
      "alternate" : null
    }, {
      "href" : "https://i2.wp.com/img.abctruyen.xyz/uploads/19599/chuong-32-2/5.jpg",
      "type" : "image/jpeg",
      "bitrate" : 0,
      "duration" : 0,
      "title" : null,
      "properties" : null,
      "alternate" : null
    } ]
  }, {
    "href" : "https://raw.githubusercontent.com/tracuumasothue40/comic_storage_two9/main/IMAGE/IMAGE_5777b5be966994190e6058da30b0f6c6_08e945681c92b9f4a36b14e7b854ff02_63ad4692354776195d82d7ddf88a335d.jpg",
    "type" : "image/jpeg",
    "bitrate" : 0,
    "duration" : 0,
    "title" : null,
    "properties" : null,
    "alternate" : [ {
      "href" : "https://img.abctruyen.xyz/uploads/19599/chuong-32-2/6.jpg",
      "type" : "image/jpeg",
      "bitrate" : 0,
      "duration" : 0,
      "title" : null,
      "properties" : null,
      "alternate" : null
    }, {
      "href" : "https://i2.wp.com/img.abctruyen.xyz/uploads/19599/chuong-32-2/6.jpg",
      "type" : "image/jpeg",
      "bitrate" : 0,
      "duration" : 0,
      "title" : null,
      "properties" : null,
      "alternate" : null
    } ]
  }, {
    "href" : "https://raw.githubusercontent.com/tracuumasothue40/comic_storage_two9/main/IMAGE/IMAGE_5777b5be966994190e6058da30b0f6c6_08e945681c92b9f4a36b14e7b854ff02_2205213becc02c98511f3d72a8ed595c.jpg",
    "type" : "image/jpeg",
    "bitrate" : 0,
    "duration" : 0,
    "title" : null,
    "properties" : null,
    "alternate" : [ {
      "href" : "https://img.abctruyen.xyz/uploads/19599/chuong-32-2/7.jpg",
      "type" : "image/jpeg",
      "bitrate" : 0,
      "duration" : 0,
      "title" : null,
      "properties" : null,
      "alternate" : null
    }, {
      "href" : "https://i2.wp.com/img.abctruyen.xyz/uploads/19599/chuong-32-2/7.jpg",
      "type" : "image/jpeg",
      "bitrate" : 0,
      "duration" : 0,
      "title" : null,
      "properties" : null,
      "alternate" : null
    } ]
  }, {
    "href" : "https://raw.githubusercontent.com/tracuumasothue40/comic_storage_two9/main/IMAGE/IMAGE_5777b5be966994190e6058da30b0f6c6_08e945681c92b9f4a36b14e7b854ff02_a39a2238647538736acd5ded35dcc4ef.jpg",
    "type" : "image/jpeg",
    "bitrate" : 0,
    "duration" : 0,
    "title" : null,
    "properties" : null,
    "alternate" : [ {
      "href" : "https://img.abctruyen.xyz/uploads/19599/chuong-32-2/8.jpg",
      "type" : "image/jpeg",
      "bitrate" : 0,
      "duration" : 0,
      "title" : null,
      "properties" : null,
      "alternate" : null
    }, {
      "href" : "https://i2.wp.com/img.abctruyen.xyz/uploads/19599/chuong-32-2/8.jpg",
      "type" : "image/jpeg",
      "bitrate" : 0,
      "duration" : 0,
      "title" : null,
      "properties" : null,
      "alternate" : null
    } ]
  }, {
    "href" : "https://raw.githubusercontent.com/tracuumasothue40/comic_storage_two9/main/IMAGE/IMAGE_5777b5be966994190e6058da30b0f6c6_08e945681c92b9f4a36b14e7b854ff02_d80db1b43d2f6891ccf8db65fcb0a753.jpg",
    "type" : "image/jpeg",
    "bitrate" : 0,
    "duration" : 0,
    "title" : null,
    "properties" : null,
    "alternate" : [ {
      "href" : "https://img.abctruyen.xyz/uploads/19599/chuong-32-2/9.jpg",
      "type" : "image/jpeg",
      "bitrate" : 0,
      "duration" : 0,
      "title" : null,
      "properties" : null,
      "alternate" : null
    }, {
      "href" : "https://i2.wp.com/img.abctruyen.xyz/uploads/19599/chuong-32-2/9.jpg",
      "type" : "image/jpeg",
      "bitrate" : 0,
      "duration" : 0,
      "title" : null,
      "properties" : null,
      "alternate" : null
    } ]
  }, {
    "href" : "https://raw.githubusercontent.com/tracuumasothue40/comic_storage_two9/main/IMAGE/IMAGE_5777b5be966994190e6058da30b0f6c6_08e945681c92b9f4a36b14e7b854ff02_8b639834d16bfcd4576a007a17520cc1.jpg",
    "type" : "image/jpeg",
    "bitrate" : 0,
    "duration" : 0,
    "title" : null,
    "properties" : null,
    "alternate" : [ {
      "href" : "https://img.abctruyen.xyz/uploads/19599/chuong-32-2/10.jpg",
      "type" : "image/jpeg",
      "bitrate" : 0,
      "duration" : 0,
      "title" : null,
      "properties" : null,
      "alternate" : null
    }, {
      "href" : "https://i2.wp.com/img.abctruyen.xyz/uploads/19599/chuong-32-2/10.jpg",
      "type" : "image/jpeg",
      "bitrate" : 0,
      "duration" : 0,
      "title" : null,
      "properties" : null,
      "alternate" : null
    } ]
  }, {
    "href" : "https://raw.githubusercontent.com/tracuumasothue40/comic_storage_two9/main/IMAGE/IMAGE_5777b5be966994190e6058da30b0f6c6_08e945681c92b9f4a36b14e7b854ff02_89a57f8e0186a38bbd396b074c131f27.jpg",
    "type" : "image/jpeg",
    "bitrate" : 0,
    "duration" : 0,
    "title" : null,
    "properties" : null,
    "alternate" : [ {
      "href" : "https://img.abctruyen.xyz/uploads/19599/chuong-32-2/11.jpg",
      "type" : "image/jpeg",
      "bitrate" : 0,
      "duration" : 0,
      "title" : null,
      "properties" : null,
      "alternate" : null
    }, {
      "href" : "https://i2.wp.com/img.abctruyen.xyz/uploads/19599/chuong-32-2/11.jpg",
      "type" : "image/jpeg",
      "bitrate" : 0,
      "duration" : 0,
      "title" : null,
      "properties" : null,
      "alternate" : null
    } ]
  }, {
    "href" : "https://raw.githubusercontent.com/tracuumasothue40/comic_storage_two9/main/IMAGE/IMAGE_5777b5be966994190e6058da30b0f6c6_08e945681c92b9f4a36b14e7b854ff02_2ce87ba45702625f865e275570697f7e.jpg",
    "type" : "image/jpeg",
    "bitrate" : 0,
    "duration" : 0,
    "title" : null,
    "properties" : null,
    "alternate" : [ {
      "href" : "https://img.abctruyen.xyz/uploads/19599/chuong-32-2/12.jpg",
      "type" : "image/jpeg",
      "bitrate" : 0,
      "duration" : 0,
      "title" : null,
      "properties" : null,
      "alternate" : null
    }, {
      "href" : "https://i2.wp.com/img.abctruyen.xyz/uploads/19599/chuong-32-2/12.jpg",
      "type" : "image/jpeg",
      "bitrate" : 0,
      "duration" : 0,
      "title" : null,
      "properties" : null,
      "alternate" : null
    } ]
  }, {
    "href" : "https://raw.githubusercontent.com/tracuumasothue40/comic_storage_two9/main/IMAGE/IMAGE_5777b5be966994190e6058da30b0f6c6_08e945681c92b9f4a36b14e7b854ff02_62db32ddd13678a8763c28ebf242c0d4.jpg",
    "type" : "image/jpeg",
    "bitrate" : 0,
    "duration" : 0,
    "title" : null,
    "properties" : null,
    "alternate" : [ {
      "href" : "https://img.abctruyen.xyz/uploads/19599/chuong-32-2/13.jpg",
      "type" : "image/jpeg",
      "bitrate" : 0,
      "duration" : 0,
      "title" : null,
      "properties" : null,
      "alternate" : null
    }, {
      "href" : "https://i2.wp.com/img.abctruyen.xyz/uploads/19599/chuong-32-2/13.jpg",
      "type" : "image/jpeg",
      "bitrate" : 0,
      "duration" : 0,
      "title" : null,
      "properties" : null,
      "alternate" : null
    } ]
  }, {
    "href" : "https://raw.githubusercontent.com/tracuumasothue40/comic_storage_two9/main/IMAGE/IMAGE_5777b5be966994190e6058da30b0f6c6_08e945681c92b9f4a36b14e7b854ff02_0cbcb45041fdc9dbdc0fbb1138b3a4dc.jpg",
    "type" : "image/jpeg",
    "bitrate" : 0,
    "duration" : 0,
    "title" : null,
    "properties" : null,
    "alternate" : [ {
      "href" : "https://img.abctruyen.xyz/uploads/19599/chuong-32-2/14.jpg",
      "type" : "image/jpeg",
      "bitrate" : 0,
      "duration" : 0,
      "title" : null,
      "properties" : null,
      "alternate" : null
    }, {
      "href" : "https://i2.wp.com/img.abctruyen.xyz/uploads/19599/chuong-32-2/14.jpg",
      "type" : "image/jpeg",
      "bitrate" : 0,
      "duration" : 0,
      "title" : null,
      "properties" : null,
      "alternate" : null
    } ]
  }, {
    "href" : "https://raw.githubusercontent.com/tracuumasothue40/comic_storage_two9/main/IMAGE/IMAGE_5777b5be966994190e6058da30b0f6c6_08e945681c92b9f4a36b14e7b854ff02_a2ad81148e64cb0231ec5592ab4f7929.jpg",
    "type" : "image/jpeg",
    "bitrate" : 0,
    "duration" : 0,
    "title" : null,
    "properties" : null,
    "alternate" : [ {
      "href" : "https://img.abctruyen.xyz/uploads/19599/chuong-32-2/15.jpg",
      "type" : "image/jpeg",
      "bitrate" : 0,
      "duration" : 0,
      "title" : null,
      "properties" : null,
      "alternate" : null
    }, {
      "href" : "https://i2.wp.com/img.abctruyen.xyz/uploads/19599/chuong-32-2/15.jpg",
      "type" : "image/jpeg",
      "bitrate" : 0,
      "duration" : 0,
      "title" : null,
      "properties" : null,
      "alternate" : null
    } ]
  }, {
    "href" : "https://raw.githubusercontent.com/tracuumasothue40/comic_storage_two9/main/IMAGE/IMAGE_5777b5be966994190e6058da30b0f6c6_08e945681c92b9f4a36b14e7b854ff02_66e53beb7d9bd6071f720b9a69c62279.jpg",
    "type" : "image/jpeg",
    "bitrate" : 0,
    "duration" : 0,
    "title" : null,
    "properties" : null,
    "alternate" : [ {
      "href" : "https://img.abctruyen.xyz/uploads/19599/chuong-32-2/16.jpg",
      "type" : "image/jpeg",
      "bitrate" : 0,
      "duration" : 0,
      "title" : null,
      "properties" : null,
      "alternate" : null
    }, {
      "href" : "https://i2.wp.com/img.abctruyen.xyz/uploads/19599/chuong-32-2/16.jpg",
      "type" : "image/jpeg",
      "bitrate" : 0,
      "duration" : 0,
      "title" : null,
      "properties" : null,
      "alternate" : null
    } ]
  }, {
    "href" : "https://raw.githubusercontent.com/tracuumasothue40/comic_storage_two9/main/IMAGE/IMAGE_5777b5be966994190e6058da30b0f6c6_08e945681c92b9f4a36b14e7b854ff02_609cf20a83c3cee34199a7962eb8941b.jpg",
    "type" : "image/jpeg",
    "bitrate" : 0,
    "duration" : 0,
    "title" : null,
    "properties" : null,
    "alternate" : [ {
      "href" : "https://img.abctruyen.xyz/uploads/19599/chuong-32-2/17.jpg",
      "type" : "image/jpeg",
      "bitrate" : 0,
      "duration" : 0,
      "title" : null,
      "properties" : null,
      "alternate" : null
    }, {
      "href" : "https://i2.wp.com/img.abctruyen.xyz/uploads/19599/chuong-32-2/17.jpg",
      "type" : "image/jpeg",
      "bitrate" : 0,
      "duration" : 0,
      "title" : null,
      "properties" : null,
      "alternate" : null
    } ]
  }, {
    "href" : "https://raw.githubusercontent.com/tracuumasothue40/comic_storage_two9/main/IMAGE/IMAGE_5777b5be966994190e6058da30b0f6c6_08e945681c92b9f4a36b14e7b854ff02_03992ad88ba660692839b9af10526440.jpg",
    "type" : "image/jpeg",
    "bitrate" : 0,
    "duration" : 0,
    "title" : null,
    "properties" : null,
    "alternate" : [ {
      "href" : "https://img.abctruyen.xyz/uploads/19599/chuong-32-2/18.jpg",
      "type" : "image/jpeg",
      "bitrate" : 0,
      "duration" : 0,
      "title" : null,
      "properties" : null,
      "alternate" : null
    }, {
      "href" : "https://i2.wp.com/img.abctruyen.xyz/uploads/19599/chuong-32-2/18.jpg",
      "type" : "image/jpeg",
      "bitrate" : 0,
      "duration" : 0,
      "title" : null,
      "properties" : null,
      "alternate" : null
    } ]
  }, {
    "href" : "https://raw.githubusercontent.com/tracuumasothue40/comic_storage_two9/main/IMAGE/IMAGE_5777b5be966994190e6058da30b0f6c6_08e945681c92b9f4a36b14e7b854ff02_b1cebba45ea3211e6c29c3598f3d21bc.jpg",
    "type" : "image/jpeg",
    "bitrate" : 0,
    "duration" : 0,
    "title" : null,
    "properties" : null,
    "alternate" : [ {
      "href" : "https://img.abctruyen.xyz/uploads/19599/chuong-32-2/19.jpg",
      "type" : "image/jpeg",
      "bitrate" : 0,
      "duration" : 0,
      "title" : null,
      "properties" : null,
      "alternate" : null
    }, {
      "href" : "https://i2.wp.com/img.abctruyen.xyz/uploads/19599/chuong-32-2/19.jpg",
      "type" : "image/jpeg",
      "bitrate" : 0,
      "duration" : 0,
      "title" : null,
      "properties" : null,
      "alternate" : null
    } ]
  }, {
    "href" : "https://raw.githubusercontent.com/tracuumasothue40/comic_storage_two9/main/IMAGE/IMAGE_5777b5be966994190e6058da30b0f6c6_08e945681c92b9f4a36b14e7b854ff02_ad4e51cac57c95da22f200e58b910fbb.jpg",
    "type" : "image/jpeg",
    "bitrate" : 0,
    "duration" : 0,
    "title" : null,
    "properties" : null,
    "alternate" : [ {
      "href" : "https://img.abctruyen.xyz/uploads/19599/chuong-32-2/20.jpg",
      "type" : "image/jpeg",
      "bitrate" : 0,
      "duration" : 0,
      "title" : null,
      "properties" : null,
      "alternate" : null
    }, {
      "href" : "https://i2.wp.com/img.abctruyen.xyz/uploads/19599/chuong-32-2/20.jpg",
      "type" : "image/jpeg",
      "bitrate" : 0,
      "duration" : 0,
      "title" : null,
      "properties" : null,
      "alternate" : null
    } ]
  }, {
    "href" : "https://raw.githubusercontent.com/tracuumasothue40/comic_storage_two9/main/IMAGE/IMAGE_5777b5be966994190e6058da30b0f6c6_08e945681c92b9f4a36b14e7b854ff02_ff86e1af9b292f72ec8ebe65fbb53741.jpg",
    "type" : "image/jpeg",
    "bitrate" : 0,
    "duration" : 0,
    "title" : null,
    "properties" : null,
    "alternate" : [ {
      "href" : "https://img.abctruyen.xyz/uploads/19599/chuong-32-2/21.jpg",
      "type" : "image/jpeg",
      "bitrate" : 0,
      "duration" : 0,
      "title" : null,
      "properties" : null,
      "alternate" : null
    }, {
      "href" : "https://i2.wp.com/img.abctruyen.xyz/uploads/19599/chuong-32-2/21.jpg",
      "type" : "image/jpeg",
      "bitrate" : 0,
      "duration" : 0,
      "title" : null,
      "properties" : null,
      "alternate" : null
    } ]
  }, {
    "href" : "https://raw.githubusercontent.com/tracuumasothue40/comic_storage_two9/main/IMAGE/IMAGE_5777b5be966994190e6058da30b0f6c6_08e945681c92b9f4a36b14e7b854ff02_32dd9ba078ad977ee9102301d97b3ccd.jpg",
    "type" : "image/jpeg",
    "bitrate" : 0,
    "duration" : 0,
    "title" : null,
    "properties" : null,
    "alternate" : [ {
      "href" : "https://img.abctruyen.xyz/uploads/19599/chuong-32-2/22.jpg",
      "type" : "image/jpeg",
      "bitrate" : 0,
      "duration" : 0,
      "title" : null,
      "properties" : null,
      "alternate" : null
    }, {
      "href" : "https://i2.wp.com/img.abctruyen.xyz/uploads/19599/chuong-32-2/22.jpg",
      "type" : "image/jpeg",
      "bitrate" : 0,
      "duration" : 0,
      "title" : null,
      "properties" : null,
      "alternate" : null
    } ]
  }, {
    "href" : "https://raw.githubusercontent.com/tracuumasothue40/comic_storage_two9/main/IMAGE/IMAGE_5777b5be966994190e6058da30b0f6c6_08e945681c92b9f4a36b14e7b854ff02_4ea58c4ee9f010231b095e237fa35e20.jpg",
    "type" : "image/jpeg",
    "bitrate" : 0,
    "duration" : 0,
    "title" : null,
    "properties" : null,
    "alternate" : [ {
      "href" : "https://img.abctruyen.xyz/uploads/19599/chuong-32-2/23.jpg",
      "type" : "image/jpeg",
      "bitrate" : 0,
      "duration" : 0,
      "title" : null,
      "properties" : null,
      "alternate" : null
    }, {
      "href" : "https://i2.wp.com/img.abctruyen.xyz/uploads/19599/chuong-32-2/23.jpg",
      "type" : "image/jpeg",
      "bitrate" : 0,
      "duration" : 0,
      "title" : null,
      "properties" : null,
      "alternate" : null
    } ]
  }, {
    "href" : "https://raw.githubusercontent.com/tracuumasothue40/comic_storage_two9/main/IMAGE/IMAGE_5777b5be966994190e6058da30b0f6c6_08e945681c92b9f4a36b14e7b854ff02_74394a7606d8baaa961dc50d22ce8fd4.jpg",
    "type" : "image/jpeg",
    "bitrate" : 0,
    "duration" : 0,
    "title" : null,
    "properties" : null,
    "alternate" : [ {
      "href" : "https://img.abctruyen.xyz/uploads/19599/chuong-32-2/24.jpg",
      "type" : "image/jpeg",
      "bitrate" : 0,
      "duration" : 0,
      "title" : null,
      "properties" : null,
      "alternate" : null
    }, {
      "href" : "https://i2.wp.com/img.abctruyen.xyz/uploads/19599/chuong-32-2/24.jpg",
      "type" : "image/jpeg",
      "bitrate" : 0,
      "duration" : 0,
      "title" : null,
      "properties" : null,
      "alternate" : null
    } ]
  }, {
    "href" : "https://raw.githubusercontent.com/tracuumasothue40/comic_storage_two9/main/IMAGE/IMAGE_5777b5be966994190e6058da30b0f6c6_08e945681c92b9f4a36b14e7b854ff02_00e02ed08c687fc741ac5350973e0e7d.jpg",
    "type" : "image/jpeg",
    "bitrate" : 0,
    "duration" : 0,
    "title" : null,
    "properties" : null,
    "alternate" : [ {
      "href" : "https://img.abctruyen.xyz/uploads/19599/chuong-32-2/25.jpg",
      "type" : "image/jpeg",
      "bitrate" : 0,
      "duration" : 0,
      "title" : null,
      "properties" : null,
      "alternate" : null
    }, {
      "href" : "https://i2.wp.com/img.abctruyen.xyz/uploads/19599/chuong-32-2/25.jpg",
      "type" : "image/jpeg",
      "bitrate" : 0,
      "duration" : 0,
      "title" : null,
      "properties" : null,
      "alternate" : null
    } ]
  }, {
    "href" : "https://raw.githubusercontent.com/tracuumasothue40/comic_storage_two9/main/IMAGE/IMAGE_5777b5be966994190e6058da30b0f6c6_08e945681c92b9f4a36b14e7b854ff02_16db064b82be7f0f6badde09b099d3e6.jpg",
    "type" : "image/jpeg",
    "bitrate" : 0,
    "duration" : 0,
    "title" : null,
    "properties" : null,
    "alternate" : [ {
      "href" : "https://img.abctruyen.xyz/uploads/19599/chuong-32-2/26.jpg",
      "type" : "image/jpeg",
      "bitrate" : 0,
      "duration" : 0,
      "title" : null,
      "properties" : null,
      "alternate" : null
    }, {
      "href" : "https://i2.wp.com/img.abctruyen.xyz/uploads/19599/chuong-32-2/26.jpg",
      "type" : "image/jpeg",
      "bitrate" : 0,
      "duration" : 0,
      "title" : null,
      "properties" : null,
      "alternate" : null
    } ]
  }, {
    "href" : "https://raw.githubusercontent.com/tracuumasothue40/comic_storage_two9/main/IMAGE/IMAGE_5777b5be966994190e6058da30b0f6c6_08e945681c92b9f4a36b14e7b854ff02_f9dcba098a3fc3291b32792e47b06db3.jpg",
    "type" : "image/jpeg",
    "bitrate" : 0,
    "duration" : 0,
    "title" : null,
    "properties" : null,
    "alternate" : [ {
      "href" : "https://img.abctruyen.xyz/uploads/19599/chuong-32-2/27.jpg",
      "type" : "image/jpeg",
      "bitrate" : 0,
      "duration" : 0,
      "title" : null,
      "properties" : null,
      "alternate" : null
    }, {
      "href" : "https://i2.wp.com/img.abctruyen.xyz/uploads/19599/chuong-32-2/27.jpg",
      "type" : "image/jpeg",
      "bitrate" : 0,
      "duration" : 0,
      "title" : null,
      "properties" : null,
      "alternate" : null
    } ]
  }, {
    "href" : "https://raw.githubusercontent.com/tracuumasothue40/comic_storage_two9/main/IMAGE/IMAGE_5777b5be966994190e6058da30b0f6c6_08e945681c92b9f4a36b14e7b854ff02_ad79ab8713e8aafdfb88323e7a4e8751.jpg",
    "type" : "image/jpeg",
    "bitrate" : 0,
    "duration" : 0,
    "title" : null,
    "properties" : null,
    "alternate" : [ {
      "href" : "https://img.abctruyen.xyz/uploads/19599/chuong-32-2/28.jpg",
      "type" : "image/jpeg",
      "bitrate" : 0,
      "duration" : 0,
      "title" : null,
      "properties" : null,
      "alternate" : null
    }, {
      "href" : "https://i2.wp.com/img.abctruyen.xyz/uploads/19599/chuong-32-2/28.jpg",
      "type" : "image/jpeg",
      "bitrate" : 0,
      "duration" : 0,
      "title" : null,
      "properties" : null,
      "alternate" : null
    } ]
  }, {
    "href" : "https://raw.githubusercontent.com/tracuumasothue40/comic_storage_two9/main/IMAGE/IMAGE_5777b5be966994190e6058da30b0f6c6_08e945681c92b9f4a36b14e7b854ff02_4eee02de7e1b20fd9bcd17a601ebd93b.jpg",
    "type" : "image/jpeg",
    "bitrate" : 0,
    "duration" : 0,
    "title" : null,
    "properties" : null,
    "alternate" : [ {
      "href" : "https://img.abctruyen.xyz/uploads/19599/chuong-32-2/29.jpg",
      "type" : "image/jpeg",
      "bitrate" : 0,
      "duration" : 0,
      "title" : null,
      "properties" : null,
      "alternate" : null
    }, {
      "href" : "https://i2.wp.com/img.abctruyen.xyz/uploads/19599/chuong-32-2/29.jpg",
      "type" : "image/jpeg",
      "bitrate" : 0,
      "duration" : 0,
      "title" : null,
      "properties" : null,
      "alternate" : null
    } ]
  }, {
    "href" : "https://raw.githubusercontent.com/tracuumasothue40/comic_storage_two9/main/IMAGE/IMAGE_5777b5be966994190e6058da30b0f6c6_08e945681c92b9f4a36b14e7b854ff02_b116feb5c4f55218870500ac2a5996f6.jpg",
    "type" : "image/jpeg",
    "bitrate" : 0,
    "duration" : 0,
    "title" : null,
    "properties" : null,
    "alternate" : [ {
      "href" : "https://img.abctruyen.xyz/uploads/19599/chuong-32-2/30.jpg",
      "type" : "image/jpeg",
      "bitrate" : 0,
      "duration" : 0,
      "title" : null,
      "properties" : null,
      "alternate" : null
    }, {
      "href" : "https://i2.wp.com/img.abctruyen.xyz/uploads/19599/chuong-32-2/30.jpg",
      "type" : "image/jpeg",
      "bitrate" : 0,
      "duration" : 0,
      "title" : null,
      "properties" : null,
      "alternate" : null
    } ]
  }, {
    "href" : "https://raw.githubusercontent.com/tracuumasothue40/comic_storage_two9/main/IMAGE/IMAGE_5777b5be966994190e6058da30b0f6c6_08e945681c92b9f4a36b14e7b854ff02_27b5d39f3d00b9226f8d2d55da640805.jpg",
    "type" : "image/jpeg",
    "bitrate" : 0,
    "duration" : 0,
    "title" : null,
    "properties" : null,
    "alternate" : [ {
      "href" : "https://img.abctruyen.xyz/uploads/19599/chuong-32-2/31.jpg",
      "type" : "image/jpeg",
      "bitrate" : 0,
      "duration" : 0,
      "title" : null,
      "properties" : null,
      "alternate" : null
    }, {
      "href" : "https://i2.wp.com/img.abctruyen.xyz/uploads/19599/chuong-32-2/31.jpg",
      "type" : "image/jpeg",
      "bitrate" : 0,
      "duration" : 0,
      "title" : null,
      "properties" : null,
      "alternate" : null
    } ]
  }, {
    "href" : "https://raw.githubusercontent.com/tracuumasothue40/comic_storage_two9/main/IMAGE/IMAGE_5777b5be966994190e6058da30b0f6c6_08e945681c92b9f4a36b14e7b854ff02_25714154a8faf4b3879f3d1c60d6c689.jpg",
    "type" : "image/jpeg",
    "bitrate" : 0,
    "duration" : 0,
    "title" : null,
    "properties" : null,
    "alternate" : [ {
      "href" : "https://img.abctruyen.xyz/uploads/19599/chuong-32-2/32.jpg",
      "type" : "image/jpeg",
      "bitrate" : 0,
      "duration" : 0,
      "title" : null,
      "properties" : null,
      "alternate" : null
    }, {
      "href" : "https://i2.wp.com/img.abctruyen.xyz/uploads/19599/chuong-32-2/32.jpg",
      "type" : "image/jpeg",
      "bitrate" : 0,
      "duration" : 0,
      "title" : null,
      "properties" : null,
      "alternate" : null
    } ]
  }, {
    "href" : "https://raw.githubusercontent.com/tracuumasothue40/comic_storage_two9/main/IMAGE/IMAGE_5777b5be966994190e6058da30b0f6c6_08e945681c92b9f4a36b14e7b854ff02_4b9704d427d88c25d7ebd22d0d9d3b4c.jpg",
    "type" : "image/jpeg",
    "bitrate" : 0,
    "duration" : 0,
    "title" : null,
    "properties" : null,
    "alternate" : [ {
      "href" : "https://img.abctruyen.xyz/uploads/19599/chuong-32-2/33.jpg",
      "type" : "image/jpeg",
      "bitrate" : 0,
      "duration" : 0,
      "title" : null,
      "properties" : null,
      "alternate" : null
    }, {
      "href" : "https://i2.wp.com/img.abctruyen.xyz/uploads/19599/chuong-32-2/33.jpg",
      "type" : "image/jpeg",
      "bitrate" : 0,
      "duration" : 0,
      "title" : null,
      "properties" : null,
      "alternate" : null
    } ]
  }, {
    "href" : "https://raw.githubusercontent.com/tracuumasothue40/comic_storage_two9/main/IMAGE/IMAGE_5777b5be966994190e6058da30b0f6c6_08e945681c92b9f4a36b14e7b854ff02_671b949e48db88e43b4617b9ec1a8a52.jpg",
    "type" : "image/jpeg",
    "bitrate" : 0,
    "duration" : 0,
    "title" : null,
    "properties" : null,
    "alternate" : [ {
      "href" : "https://img.abctruyen.xyz/uploads/19599/chuong-32-2/34.jpg",
      "type" : "image/jpeg",
      "bitrate" : 0,
      "duration" : 0,
      "title" : null,
      "properties" : null,
      "alternate" : null
    }, {
      "href" : "https://i2.wp.com/img.abctruyen.xyz/uploads/19599/chuong-32-2/34.jpg",
      "type" : "image/jpeg",
      "bitrate" : 0,
      "duration" : 0,
      "title" : null,
      "properties" : null,
      "alternate" : null
    } ]
  }, {
    "href" : "https://raw.githubusercontent.com/tracuumasothue40/comic_storage_two9/main/IMAGE/IMAGE_5777b5be966994190e6058da30b0f6c6_08e945681c92b9f4a36b14e7b854ff02_46c279622a58eb525cf35532695b6ab3.jpg",
    "type" : "image/jpeg",
    "bitrate" : 0,
    "duration" : 0,
    "title" : null,
    "properties" : null,
    "alternate" : [ {
      "href" : "https://img.abctruyen.xyz/uploads/19599/chuong-32-2/35.jpg",
      "type" : "image/jpeg",
      "bitrate" : 0,
      "duration" : 0,
      "title" : null,
      "properties" : null,
      "alternate" : null
    }, {
      "href" : "https://i2.wp.com/img.abctruyen.xyz/uploads/19599/chuong-32-2/35.jpg",
      "type" : "image/jpeg",
      "bitrate" : 0,
      "duration" : 0,
      "title" : null,
      "properties" : null,
      "alternate" : null
    } ]
  }, {
    "href" : "https://raw.githubusercontent.com/tracuumasothue40/comic_storage_two9/main/IMAGE/IMAGE_5777b5be966994190e6058da30b0f6c6_08e945681c92b9f4a36b14e7b854ff02_893e9a3f7c27b2d51a431703b3187643.jpg",
    "type" : "image/jpeg",
    "bitrate" : 0,
    "duration" : 0,
    "title" : null,
    "properties" : null,
    "alternate" : [ {
      "href" : "https://img.abctruyen.xyz/uploads/19599/chuong-32-2/36.jpg",
      "type" : "image/jpeg",
      "bitrate" : 0,
      "duration" : 0,
      "title" : null,
      "properties" : null,
      "alternate" : null
    }, {
      "href" : "https://i2.wp.com/img.abctruyen.xyz/uploads/19599/chuong-32-2/36.jpg",
      "type" : "image/jpeg",
      "bitrate" : 0,
      "duration" : 0,
      "title" : null,
      "properties" : null,
      "alternate" : null
    } ]
  }, {
    "href" : "https://raw.githubusercontent.com/tracuumasothue40/comic_storage_two9/main/IMAGE/IMAGE_5777b5be966994190e6058da30b0f6c6_08e945681c92b9f4a36b14e7b854ff02_d117e175d033dc34530d6aab2974bcc7.jpg",
    "type" : "image/jpeg",
    "bitrate" : 0,
    "duration" : 0,
    "title" : null,
    "properties" : null,
    "alternate" : [ {
      "href" : "https://img.abctruyen.xyz/uploads/19599/chuong-32-2/37.jpg",
      "type" : "image/jpeg",
      "bitrate" : 0,
      "duration" : 0,
      "title" : null,
      "properties" : null,
      "alternate" : null
    }, {
      "href" : "https://i2.wp.com/img.abctruyen.xyz/uploads/19599/chuong-32-2/37.jpg",
      "type" : "image/jpeg",
      "bitrate" : 0,
      "duration" : 0,
      "title" : null,
      "properties" : null,
      "alternate" : null
    } ]
  }, {
    "href" : "https://raw.githubusercontent.com/tracuumasothue40/comic_storage_two9/main/IMAGE/IMAGE_5777b5be966994190e6058da30b0f6c6_08e945681c92b9f4a36b14e7b854ff02_afd81427f8548a29701fff8e59b535ff.jpg",
    "type" : "image/jpeg",
    "bitrate" : 0,
    "duration" : 0,
    "title" : null,
    "properties" : null,
    "alternate" : [ {
      "href" : "https://img.abctruyen.xyz/uploads/19599/chuong-32-2/38.jpg",
      "type" : "image/jpeg",
      "bitrate" : 0,
      "duration" : 0,
      "title" : null,
      "properties" : null,
      "alternate" : null
    }, {
      "href" : "https://i2.wp.com/img.abctruyen.xyz/uploads/19599/chuong-32-2/38.jpg",
      "type" : "image/jpeg",
      "bitrate" : 0,
      "duration" : 0,
      "title" : null,
      "properties" : null,
      "alternate" : null
    } ]
  }, {
    "href" : "https://raw.githubusercontent.com/tracuumasothue40/comic_storage_two9/main/IMAGE/IMAGE_5777b5be966994190e6058da30b0f6c6_08e945681c92b9f4a36b14e7b854ff02_897bf7c5b1465dae18630703f0824b24.jpg",
    "type" : "image/jpeg",
    "bitrate" : 0,
    "duration" : 0,
    "title" : null,
    "properties" : null,
    "alternate" : [ {
      "href" : "https://img.abctruyen.xyz/uploads/19599/chuong-32-2/39.jpg",
      "type" : "image/jpeg",
      "bitrate" : 0,
      "duration" : 0,
      "title" : null,
      "properties" : null,
      "alternate" : null
    }, {
      "href" : "https://i2.wp.com/img.abctruyen.xyz/uploads/19599/chuong-32-2/39.jpg",
      "type" : "image/jpeg",
      "bitrate" : 0,
      "duration" : 0,
      "title" : null,
      "properties" : null,
      "alternate" : null
    } ]
  }, {
    "href" : "https://raw.githubusercontent.com/tracuumasothue40/comic_storage_two9/main/IMAGE/IMAGE_5777b5be966994190e6058da30b0f6c6_08e945681c92b9f4a36b14e7b854ff02_6f5747cf761f43df4217c97f1304a73e.jpg",
    "type" : "image/jpeg",
    "bitrate" : 0,
    "duration" : 0,
    "title" : null,
    "properties" : null,
    "alternate" : [ {
      "href" : "https://img.abctruyen.xyz/uploads/19599/chuong-32-2/40.jpg",
      "type" : "image/jpeg",
      "bitrate" : 0,
      "duration" : 0,
      "title" : null,
      "properties" : null,
      "alternate" : null
    }, {
      "href" : "https://i2.wp.com/img.abctruyen.xyz/uploads/19599/chuong-32-2/40.jpg",
      "type" : "image/jpeg",
      "bitrate" : 0,
      "duration" : 0,
      "title" : null,
      "properties" : null,
      "alternate" : null
    } ]
  }, {
    "href" : "https://raw.githubusercontent.com/tracuumasothue40/comic_storage_two9/main/IMAGE/IMAGE_5777b5be966994190e6058da30b0f6c6_08e945681c92b9f4a36b14e7b854ff02_5d8a1b139f2a56b1b2ab1315cbb4871c.jpg",
    "type" : "image/jpeg",
    "bitrate" : 0,
    "duration" : 0,
    "title" : null,
    "properties" : null,
    "alternate" : [ {
      "href" : "https://img.abctruyen.xyz/uploads/19599/chuong-32-2/41.jpg",
      "type" : "image/jpeg",
      "bitrate" : 0,
      "duration" : 0,
      "title" : null,
      "properties" : null,
      "alternate" : null
    }, {
      "href" : "https://i2.wp.com/img.abctruyen.xyz/uploads/19599/chuong-32-2/41.jpg",
      "type" : "image/jpeg",
      "bitrate" : 0,
      "duration" : 0,
      "title" : null,
      "properties" : null,
      "alternate" : null
    } ]
  }, {
    "href" : "https://raw.githubusercontent.com/tracuumasothue40/comic_storage_two9/main/IMAGE/IMAGE_5777b5be966994190e6058da30b0f6c6_08e945681c92b9f4a36b14e7b854ff02_8937d79c3e10a672915d50d6b53e0c2c.jpg",
    "type" : "image/jpeg",
    "bitrate" : 0,
    "duration" : 0,
    "title" : null,
    "properties" : null,
    "alternate" : [ {
      "href" : "https://img.abctruyen.xyz/uploads/19599/chuong-32-2/42.jpg",
      "type" : "image/jpeg",
      "bitrate" : 0,
      "duration" : 0,
      "title" : null,
      "properties" : null,
      "alternate" : null
    }, {
      "href" : "https://i2.wp.com/img.abctruyen.xyz/uploads/19599/chuong-32-2/42.jpg",
      "type" : "image/jpeg",
      "bitrate" : 0,
      "duration" : 0,
      "title" : null,
      "properties" : null,
      "alternate" : null
    } ]
  }, {
    "href" : "https://raw.githubusercontent.com/tracuumasothue40/comic_storage_two9/main/IMAGE/IMAGE_5777b5be966994190e6058da30b0f6c6_08e945681c92b9f4a36b14e7b854ff02_d231bb5e2f5b7a2343f8446fb6b28c10.jpg",
    "type" : "image/jpeg",
    "bitrate" : 0,
    "duration" : 0,
    "title" : null,
    "properties" : null,
    "alternate" : [ {
      "href" : "https://img.abctruyen.xyz/uploads/19599/chuong-32-2/43.jpg",
      "type" : "image/jpeg",
      "bitrate" : 0,
      "duration" : 0,
      "title" : null,
      "properties" : null,
      "alternate" : null
    }, {
      "href" : "https://i2.wp.com/img.abctruyen.xyz/uploads/19599/chuong-32-2/43.jpg",
      "type" : "image/jpeg",
      "bitrate" : 0,
      "duration" : 0,
      "title" : null,
      "properties" : null,
      "alternate" : null
    } ]
  }, {
    "href" : "https://raw.githubusercontent.com/tracuumasothue40/comic_storage_two9/main/IMAGE/IMAGE_5777b5be966994190e6058da30b0f6c6_08e945681c92b9f4a36b14e7b854ff02_5bde03c696b278e85bec6bcabf3a3a95.jpg",
    "type" : "image/jpeg",
    "bitrate" : 0,
    "duration" : 0,
    "title" : null,
    "properties" : null,
    "alternate" : [ {
      "href" : "https://img.abctruyen.xyz/uploads/19599/chuong-32-2/44.jpg",
      "type" : "image/jpeg",
      "bitrate" : 0,
      "duration" : 0,
      "title" : null,
      "properties" : null,
      "alternate" : null
    }, {
      "href" : "https://i2.wp.com/img.abctruyen.xyz/uploads/19599/chuong-32-2/44.jpg",
      "type" : "image/jpeg",
      "bitrate" : 0,
      "duration" : 0,
      "title" : null,
      "properties" : null,
      "alternate" : null
    } ]
  }, {
    "href" : "https://raw.githubusercontent.com/tracuumasothue40/comic_storage_two9/main/IMAGE/IMAGE_5777b5be966994190e6058da30b0f6c6_08e945681c92b9f4a36b14e7b854ff02_97a4af934cc701312dd7ff6570384c55.jpg",
    "type" : "image/jpeg",
    "bitrate" : 0,
    "duration" : 0,
    "title" : null,
    "properties" : null,
    "alternate" : [ {
      "href" : "https://img.abctruyen.xyz/uploads/19599/chuong-32-2/45.jpg",
      "type" : "image/jpeg",
      "bitrate" : 0,
      "duration" : 0,
      "title" : null,
      "properties" : null,
      "alternate" : null
    }, {
      "href" : "https://i2.wp.com/img.abctruyen.xyz/uploads/19599/chuong-32-2/45.jpg",
      "type" : "image/jpeg",
      "bitrate" : 0,
      "duration" : 0,
      "title" : null,
      "properties" : null,
      "alternate" : null
    } ]
  }, {
    "href" : "https://raw.githubusercontent.com/tracuumasothue40/comic_storage_two9/main/IMAGE/IMAGE_5777b5be966994190e6058da30b0f6c6_08e945681c92b9f4a36b14e7b854ff02_17c55cae1cc197df24ac4a978422a92b.jpg",
    "type" : "image/jpeg",
    "bitrate" : 0,
    "duration" : 0,
    "title" : null,
    "properties" : null,
    "alternate" : [ {
      "href" : "https://img.abctruyen.xyz/uploads/19599/chuong-32-2/46.jpg",
      "type" : "image/jpeg",
      "bitrate" : 0,
      "duration" : 0,
      "title" : null,
      "properties" : null,
      "alternate" : null
    }, {
      "href" : "https://i2.wp.com/img.abctruyen.xyz/uploads/19599/chuong-32-2/46.jpg",
      "type" : "image/jpeg",
      "bitrate" : 0,
      "duration" : 0,
      "title" : null,
      "properties" : null,
      "alternate" : null
    } ]
  }, {
    "href" : "https://raw.githubusercontent.com/tracuumasothue40/comic_storage_two9/main/IMAGE/IMAGE_5777b5be966994190e6058da30b0f6c6_08e945681c92b9f4a36b14e7b854ff02_3b37813bdc2790726089d1e908bca096.jpg",
    "type" : "image/jpeg",
    "bitrate" : 0,
    "duration" : 0,
    "title" : null,
    "properties" : null,
    "alternate" : [ {
      "href" : "https://img.abctruyen.xyz/uploads/19599/chuong-32-2/47.jpg",
      "type" : "image/jpeg",
      "bitrate" : 0,
      "duration" : 0,
      "title" : null,
      "properties" : null,
      "alternate" : null
    }, {
      "href" : "https://i2.wp.com/img.abctruyen.xyz/uploads/19599/chuong-32-2/47.jpg",
      "type" : "image/jpeg",
      "bitrate" : 0,
      "duration" : 0,
      "title" : null,
      "properties" : null,
      "alternate" : null
    } ]
  }, {
    "href" : "https://raw.githubusercontent.com/tracuumasothue40/comic_storage_two9/main/IMAGE/IMAGE_5777b5be966994190e6058da30b0f6c6_08e945681c92b9f4a36b14e7b854ff02_8e19446426f429af7b2859bc51a69c54.jpg",
    "type" : "image/jpeg",
    "bitrate" : 0,
    "duration" : 0,
    "title" : null,
    "properties" : null,
    "alternate" : [ {
      "href" : "https://img.abctruyen.xyz/uploads/19599/chuong-32-2/48.jpg",
      "type" : "image/jpeg",
      "bitrate" : 0,
      "duration" : 0,
      "title" : null,
      "properties" : null,
      "alternate" : null
    }, {
      "href" : "https://i2.wp.com/img.abctruyen.xyz/uploads/19599/chuong-32-2/48.jpg",
      "type" : "image/jpeg",
      "bitrate" : 0,
      "duration" : 0,
      "title" : null,
      "properties" : null,
      "alternate" : null
    } ]
  }, {
    "href" : "https://raw.githubusercontent.com/tracuumasothue40/comic_storage_two9/main/IMAGE/IMAGE_5777b5be966994190e6058da30b0f6c6_08e945681c92b9f4a36b14e7b854ff02_a5f109e00fa2280af09ce21ade159d14.jpg",
    "type" : "image/jpeg",
    "bitrate" : 0,
    "duration" : 0,
    "title" : null,
    "properties" : null,
    "alternate" : [ {
      "href" : "https://img.abctruyen.xyz/uploads/19599/chuong-32-2/49.jpg",
      "type" : "image/jpeg",
      "bitrate" : 0,
      "duration" : 0,
      "title" : null,
      "properties" : null,
      "alternate" : null
    }, {
      "href" : "https://i2.wp.com/img.abctruyen.xyz/uploads/19599/chuong-32-2/49.jpg",
      "type" : "image/jpeg",
      "bitrate" : 0,
      "duration" : 0,
      "title" : null,
      "properties" : null,
      "alternate" : null
    } ]
  }, {
    "href" : "https://raw.githubusercontent.com/tracuumasothue40/comic_storage_two9/main/IMAGE/IMAGE_5777b5be966994190e6058da30b0f6c6_08e945681c92b9f4a36b14e7b854ff02_7d59016eeb0eba62fa36a7e0c585403d.jpg",
    "type" : "image/jpeg",
    "bitrate" : 0,
    "duration" : 0,
    "title" : null,
    "properties" : null,
    "alternate" : [ {
      "href" : "https://img.abctruyen.xyz/uploads/19599/chuong-32-2/50.jpg",
      "type" : "image/jpeg",
      "bitrate" : 0,
      "duration" : 0,
      "title" : null,
      "properties" : null,
      "alternate" : null
    }, {
      "href" : "https://i2.wp.com/img.abctruyen.xyz/uploads/19599/chuong-32-2/50.jpg",
      "type" : "image/jpeg",
      "bitrate" : 0,
      "duration" : 0,
      "title" : null,
      "properties" : null,
      "alternate" : null
    } ]
  }, {
    "href" : "https://raw.githubusercontent.com/tracuumasothue40/comic_storage_two9/main/IMAGE/IMAGE_5777b5be966994190e6058da30b0f6c6_08e945681c92b9f4a36b14e7b854ff02_d2405cd4ef9f174352e2589c706a0039.jpg",
    "type" : "image/jpeg",
    "bitrate" : 0,
    "duration" : 0,
    "title" : null,
    "properties" : null,
    "alternate" : [ {
      "href" : "https://img.abctruyen.xyz/uploads/19599/chuong-32-2/51.jpg",
      "type" : "image/jpeg",
      "bitrate" : 0,
      "duration" : 0,
      "title" : null,
      "properties" : null,
      "alternate" : null
    }, {
      "href" : "https://i2.wp.com/img.abctruyen.xyz/uploads/19599/chuong-32-2/51.jpg",
      "type" : "image/jpeg",
      "bitrate" : 0,
      "duration" : 0,
      "title" : null,
      "properties" : null,
      "alternate" : null
    } ]
  }, {
    "href" : "https://raw.githubusercontent.com/tracuumasothue40/comic_storage_two9/main/IMAGE/IMAGE_5777b5be966994190e6058da30b0f6c6_08e945681c92b9f4a36b14e7b854ff02_e42db5cb6fb39ecf095a72dd7ac8b3ae.jpg",
    "type" : "image/jpeg",
    "bitrate" : 0,
    "duration" : 0,
    "title" : null,
    "properties" : null,
    "alternate" : [ {
      "href" : "https://img.abctruyen.xyz/uploads/19599/chuong-32-2/52.jpg",
      "type" : "image/jpeg",
      "bitrate" : 0,
      "duration" : 0,
      "title" : null,
      "properties" : null,
      "alternate" : null
    }, {
      "href" : "https://i2.wp.com/img.abctruyen.xyz/uploads/19599/chuong-32-2/52.jpg",
      "type" : "image/jpeg",
      "bitrate" : 0,
      "duration" : 0,
      "title" : null,
      "properties" : null,
      "alternate" : null
    } ]
  }, {
    "href" : "https://raw.githubusercontent.com/tracuumasothue40/comic_storage_two9/main/IMAGE/IMAGE_5777b5be966994190e6058da30b0f6c6_08e945681c92b9f4a36b14e7b854ff02_232e92f2ec6d3031b7952dafba4afa83.jpg",
    "type" : "image/jpeg",
    "bitrate" : 0,
    "duration" : 0,
    "title" : null,
    "properties" : null,
    "alternate" : [ {
      "href" : "https://img.abctruyen.xyz/uploads/19599/chuong-32-2/53.jpg",
      "type" : "image/jpeg",
      "bitrate" : 0,
      "duration" : 0,
      "title" : null,
      "properties" : null,
      "alternate" : null
    }, {
      "href" : "https://i2.wp.com/img.abctruyen.xyz/uploads/19599/chuong-32-2/53.jpg",
      "type" : "image/jpeg",
      "bitrate" : 0,
      "duration" : 0,
      "title" : null,
      "properties" : null,
      "alternate" : null
    } ]
  }, {
    "href" : "https://raw.githubusercontent.com/tracuumasothue40/comic_storage_two9/main/IMAGE/IMAGE_5777b5be966994190e6058da30b0f6c6_08e945681c92b9f4a36b14e7b854ff02_e1e4d8cfbfe2870f423959ce20fdda7d.jpg",
    "type" : "image/jpeg",
    "bitrate" : 0,
    "duration" : 0,
    "title" : null,
    "properties" : null,
    "alternate" : [ {
      "href" : "https://img.abctruyen.xyz/uploads/19599/chuong-32-2/54.jpg",
      "type" : "image/jpeg",
      "bitrate" : 0,
      "duration" : 0,
      "title" : null,
      "properties" : null,
      "alternate" : null
    }, {
      "href" : "https://i2.wp.com/img.abctruyen.xyz/uploads/19599/chuong-32-2/54.jpg",
      "type" : "image/jpeg",
      "bitrate" : 0,
      "duration" : 0,
      "title" : null,
      "properties" : null,
      "alternate" : null
    } ]
  }, {
    "href" : "https://raw.githubusercontent.com/tracuumasothue40/comic_storage_two9/main/IMAGE/IMAGE_5777b5be966994190e6058da30b0f6c6_08e945681c92b9f4a36b14e7b854ff02_1a72a081bf7c39224a97b7c6b3301c0b.jpg",
    "type" : "image/jpeg",
    "bitrate" : 0,
    "duration" : 0,
    "title" : null,
    "properties" : null,
    "alternate" : [ {
      "href" : "https://img.abctruyen.xyz/uploads/19599/chuong-32-2/55.jpg",
      "type" : "image/jpeg",
      "bitrate" : 0,
      "duration" : 0,
      "title" : null,
      "properties" : null,
      "alternate" : null
    }, {
      "href" : "https://i2.wp.com/img.abctruyen.xyz/uploads/19599/chuong-32-2/55.jpg",
      "type" : "image/jpeg",
      "bitrate" : 0,
      "duration" : 0,
      "title" : null,
      "properties" : null,
      "alternate" : null
    } ]
  }, {
    "href" : "https://raw.githubusercontent.com/tracuumasothue40/comic_storage_two9/main/IMAGE/IMAGE_5777b5be966994190e6058da30b0f6c6_08e945681c92b9f4a36b14e7b854ff02_a6cdf4477d0a6706d2561871d43a73db.jpg",
    "type" : "image/jpeg",
    "bitrate" : 0,
    "duration" : 0,
    "title" : null,
    "properties" : null,
    "alternate" : [ {
      "href" : "https://img.abctruyen.xyz/uploads/19599/chuong-32-2/56.jpg",
      "type" : "image/jpeg",
      "bitrate" : 0,
      "duration" : 0,
      "title" : null,
      "properties" : null,
      "alternate" : null
    }, {
      "href" : "https://i2.wp.com/img.abctruyen.xyz/uploads/19599/chuong-32-2/56.jpg",
      "type" : "image/jpeg",
      "bitrate" : 0,
      "duration" : 0,
      "title" : null,
      "properties" : null,
      "alternate" : null
    } ]
  }, {
    "href" : "https://raw.githubusercontent.com/tracuumasothue40/comic_storage_two9/main/IMAGE/IMAGE_5777b5be966994190e6058da30b0f6c6_08e945681c92b9f4a36b14e7b854ff02_363b1364295dcff5ba58e320c1fc57b4.jpg",
    "type" : "image/jpeg",
    "bitrate" : 0,
    "duration" : 0,
    "title" : null,
    "properties" : null,
    "alternate" : [ {
      "href" : "https://img.abctruyen.xyz/uploads/19599/chuong-32-2/57.jpg",
      "type" : "image/jpeg",
      "bitrate" : 0,
      "duration" : 0,
      "title" : null,
      "properties" : null,
      "alternate" : null
    }, {
      "href" : "https://i2.wp.com/img.abctruyen.xyz/uploads/19599/chuong-32-2/57.jpg",
      "type" : "image/jpeg",
      "bitrate" : 0,
      "duration" : 0,
      "title" : null,
      "properties" : null,
      "alternate" : null
    } ]
  }, {
    "href" : "https://raw.githubusercontent.com/tracuumasothue40/comic_storage_two9/main/IMAGE/IMAGE_5777b5be966994190e6058da30b0f6c6_08e945681c92b9f4a36b14e7b854ff02_22693990c31314ea064684521056b322.jpg",
    "type" : "image/jpeg",
    "bitrate" : 0,
    "duration" : 0,
    "title" : null,
    "properties" : null,
    "alternate" : [ {
      "href" : "https://img.abctruyen.xyz/uploads/19599/chuong-32-2/58.jpg",
      "type" : "image/jpeg",
      "bitrate" : 0,
      "duration" : 0,
      "title" : null,
      "properties" : null,
      "alternate" : null
    }, {
      "href" : "https://i2.wp.com/img.abctruyen.xyz/uploads/19599/chuong-32-2/58.jpg",
      "type" : "image/jpeg",
      "bitrate" : 0,
      "duration" : 0,
      "title" : null,
      "properties" : null,
      "alternate" : null
    } ]
  }, {
    "href" : "https://raw.githubusercontent.com/tracuumasothue40/comic_storage_two9/main/IMAGE/IMAGE_5777b5be966994190e6058da30b0f6c6_08e945681c92b9f4a36b14e7b854ff02_a2d510b72cd7ce49696c82b9cda764ab.jpg",
    "type" : "image/jpeg",
    "bitrate" : 0,
    "duration" : 0,
    "title" : null,
    "properties" : null,
    "alternate" : [ {
      "href" : "https://img.abctruyen.xyz/uploads/19599/chuong-32-2/59.jpg",
      "type" : "image/jpeg",
      "bitrate" : 0,
      "duration" : 0,
      "title" : null,
      "properties" : null,
      "alternate" : null
    }, {
      "href" : "https://i2.wp.com/img.abctruyen.xyz/uploads/19599/chuong-32-2/59.jpg",
      "type" : "image/jpeg",
      "bitrate" : 0,
      "duration" : 0,
      "title" : null,
      "properties" : null,
      "alternate" : null
    } ]
  }, {
    "href" : "https://raw.githubusercontent.com/tracuumasothue40/comic_storage_two9/main/IMAGE/IMAGE_5777b5be966994190e6058da30b0f6c6_08e945681c92b9f4a36b14e7b854ff02_80c8bb38106869ba7304d9738b96ab75.jpg",
    "type" : "image/jpeg",
    "bitrate" : 0,
    "duration" : 0,
    "title" : null,
    "properties" : null,
    "alternate" : [ {
      "href" : "https://img.abctruyen.xyz/uploads/19599/chuong-32-2/60.jpg",
      "type" : "image/jpeg",
      "bitrate" : 0,
      "duration" : 0,
      "title" : null,
      "properties" : null,
      "alternate" : null
    }, {
      "href" : "https://i2.wp.com/img.abctruyen.xyz/uploads/19599/chuong-32-2/60.jpg",
      "type" : "image/jpeg",
      "bitrate" : 0,
      "duration" : 0,
      "title" : null,
      "properties" : null,
      "alternate" : null
    } ]
  }, {
    "href" : "https://raw.githubusercontent.com/tracuumasothue40/comic_storage_two9/main/IMAGE/IMAGE_5777b5be966994190e6058da30b0f6c6_08e945681c92b9f4a36b14e7b854ff02_f88711106152ebb4e21367b9c5b75d68.jpg",
    "type" : "image/jpeg",
    "bitrate" : 0,
    "duration" : 0,
    "title" : null,
    "properties" : null,
    "alternate" : [ {
      "href" : "https://img.abctruyen.xyz/uploads/19599/chuong-32-2/61.jpg",
      "type" : "image/jpeg",
      "bitrate" : 0,
      "duration" : 0,
      "title" : null,
      "properties" : null,
      "alternate" : null
    }, {
      "href" : "https://i2.wp.com/img.abctruyen.xyz/uploads/19599/chuong-32-2/61.jpg",
      "type" : "image/jpeg",
      "bitrate" : 0,
      "duration" : 0,
      "title" : null,
      "properties" : null,
      "alternate" : null
    } ]
  }, {
    "href" : "https://raw.githubusercontent.com/tracuumasothue40/comic_storage_two9/main/IMAGE/IMAGE_5777b5be966994190e6058da30b0f6c6_08e945681c92b9f4a36b14e7b854ff02_666dec0b9ba855c329239afe09d84260.jpg",
    "type" : "image/jpeg",
    "bitrate" : 0,
    "duration" : 0,
    "title" : null,
    "properties" : null,
    "alternate" : [ {
      "href" : "https://img.abctruyen.xyz/uploads/19599/chuong-32-2/62.jpg",
      "type" : "image/jpeg",
      "bitrate" : 0,
      "duration" : 0,
      "title" : null,
      "properties" : null,
      "alternate" : null
    }, {
      "href" : "https://i2.wp.com/img.abctruyen.xyz/uploads/19599/chuong-32-2/62.jpg",
      "type" : "image/jpeg",
      "bitrate" : 0,
      "duration" : 0,
      "title" : null,
      "properties" : null,
      "alternate" : null
    } ]
  } ],
  "toc" : null,
  "@context" : "https://readium.org/webpub-manifest/context.jsonld"
}